location_checker-0.1.3.dist-info/METADATA
location_checker-0.1.3.dist-info/WHEEL
location_checker-0.1.3.dist-info/licenses/LICENSE
location_checker/__init__.py
location_checker/location_checker.pyi
location_checker/location_checker.cpython-311-aarch64-linux-gnu.so
location_checker-0.1.3.dist-info/RECORD
