Metadata-Version: 2.4
Name: location-checker
Version: 0.1.3
Classifier: Programming Language :: Python :: 3
Classifier: Programming Language :: Rust
Classifier: License :: OSI Approved :: MIT License
Classifier: Operating System :: OS Independent
License-File: LICENSE
Summary: A Python-wrapped Rust Location Checker
Author: Malaa Technologies <engineeering@malaa.tech>
Author-email: Malaa Technologies <engineering@malaa.tech>
License: MIT
